{
    "https://www.business2communitymalaysia.com/en/gambling/online-baccarat-malaysia": {
        "hash": "b79e393582d9cb054166695dde787020",
        "last_checked": "2025-09-10T15:09:54.053420",
        "last_changed": "2025-09-10T15:09:54.053430"
    },
    "https://www.business2communitymalaysia.com/en/gambling/online-blackjack": {
        "hash": "b6361f775ca29bd9feba89880ecc43cf",
        "last_checked": "2025-09-10T15:09:55.310319",
        "last_changed": "2025-09-10T15:09:55.310328"
    },
    "https://www.business2communitymalaysia.com/en/gambling/fishing-games": {
        "hash": "1ad0d1de0927a9461269ee84fece1ddf",
        "last_checked": "2025-09-10T15:09:56.732534",
        "last_changed": "2025-09-10T15:09:56.732544"
    },
    "https://www.business2communitymalaysia.com/en/gambling/online-roulette-malaysia": {
        "hash": "b6ae046bd6d7729c7c44544ef48b4602",
        "last_checked": "2025-09-10T15:09:58.131892",
        "last_changed": "2025-09-10T15:09:58.131902"
    },
    "https://www.business2communitymalaysia.com/en/gambling/12play-review": {
        "hash": "d5df667f07fcd6ef54647c079d43cfc4",
        "last_checked": "2025-09-10T15:09:59.409508",
        "last_changed": "2025-09-10T15:09:59.409516"
    },
    "https://www.business2communitymalaysia.com/en/gambling/aw8-review": {
        "hash": "8a0d4a3f6fe3f2cdba01f521dac2bd52",
        "last_checked": "2025-09-10T15:10:00.883846",
        "last_changed": "2025-09-10T15:10:00.883852"
    },
    "https://www.business2communitymalaysia.com/en/gambling/md88-review": {
        "hash": "c8feb9e5bca37a3ab9b293b0f922f707",
        "last_checked": "2025-09-10T15:10:02.279285",
        "last_changed": "2025-09-10T15:10:02.279292"
    },
    "https://www.business2communitymalaysia.com/en/gambling/football-betting": {
        "hash": "6f34723f7e4995576611d3b3b2ac691d",
        "last_checked": "2025-09-10T15:10:03.573407",
        "last_changed": "2025-09-10T15:10:03.573417"
    },
    "https://www.business2communitymalaysia.com/en/gambling/esports-betting": {
        "hash": "b83bd004c8e9bd0d21404e63f4a3fec4",
        "last_checked": "2025-09-10T15:10:04.960111",
        "last_changed": "2025-09-10T15:10:04.960121"
    },
    "https://www.lb33.asia/promotion": {
        "hash": "5ce65f0874392280de52db97d9ae0154",
        "last_checked": "2025-09-10T15:10:07.091245",
        "last_changed": "2025-09-10T15:10:07.091253"
    }
}